dprMenus/ItemDecorator.py
dprMenus/Menu.py
dprMenus/MenuDecorator.py
dprMenus/MenuItem.py
dprMenus/MenuList.py
dprMenus/ScrollDir.py
dprMenus/Utils.py
dprMenus/__init__.py
dprMenus-1.9.3.dist-info/LICENSE
dprMenus-1.9.3.dist-info/METADATA
dprMenus-1.9.3.dist-info/WHEEL
dprMenus-1.9.3.dist-info/top_level.txt
dprMenus-1.9.3.dist-info/RECORD
