Metadata-Version: 2.1
Name: dprMenus
Version: 1.9.3
Summary: .dpr. Team: Menus for Mystic BBS
Home-page: https://github.com/deadbeatz/dpr_menus
Author: Analog
Author-email: analog@deadbeatz.org
License: MIT
Download-URL: https://github.com/deadbeatz/dpr_menus/archive/v1.9.3.tar.gz
Keywords: Mystic,BBS,dpr,menus
Platform: UNKNOWN
Classifier: Development Status :: 5 - Production/Stable
Classifier: License :: OSI Approved :: MIT License
Classifier: Programming Language :: Python :: 2
Classifier: Programming Language :: Python :: 2.7
